coloranalysis/__init__.py
coloranalysis/colors.py
coloranalysis-1.0.1.dist-info/LICENSE
coloranalysis-1.0.1.dist-info/METADATA
coloranalysis-1.0.1.dist-info/WHEEL
coloranalysis-1.0.1.dist-info/top_level.txt
coloranalysis-1.0.1.dist-info/RECORD
